lint_all/__init__.py
lint_all/all_linters.yaml
lint_all/lint_all.py
lint_all-0.1.2.dist-info/LICENSE
lint_all-0.1.2.dist-info/METADATA
lint_all-0.1.2.dist-info/WHEEL
lint_all-0.1.2.dist-info/entry_points.txt
lint_all-0.1.2.dist-info/top_level.txt
lint_all-0.1.2.dist-info/RECORD
