Metadata-Version: 2.1
Name: lint_all
Version: 0.1.2
Summary: A meta linter to run all linters
Author-email: Shir Granot Peled <shirpeled+lintall@gmail.com>
License: Apache-2.0
Requires-Python: >=3.8
License-File: LICENSE
Requires-Dist: gitdb
Requires-Dist: GitPython
Requires-Dist: pyyaml
